calcifer_pde/__init__.py
calcifer_pde/boundary.py
calcifer_pde/calcifer.py
calcifer_pde/diff.py
calcifer_pde/domain.py
calcifer_pde/geometry.py
calcifer_pde-0.1.1.dist-info/LICENSE
calcifer_pde-0.1.1.dist-info/METADATA
calcifer_pde-0.1.1.dist-info/WHEEL
calcifer_pde-0.1.1.dist-info/top_level.txt
calcifer_pde-0.1.1.dist-info/RECORD
