Metadata-Version: 2.1
Name: calcifer-pde
Version: 0.1.1
Summary: Python Poisson solver on curvilinear 2-D grid
Home-page: UNKNOWN
Author: COOP
Author-email: coop@cerfacs.fr
License: UNKNOWN
Keywords: PDE,temperature,solver,poisson,curvilinear grid
Platform: UNKNOWN
Classifier: Programming Language :: Python :: 3.6
Classifier: Programming Language :: Python :: 3.7
Requires-Dist: numpy
Requires-Dist: scipy
Requires-Dist: arnica
